streamlit_card/__init__.py
streamlit_card/frontend/build/asset-manifest.json
streamlit_card/frontend/build/bootstrap.min.css
streamlit_card/frontend/build/bootstrap.min.css.map
streamlit_card/frontend/build/index.html
streamlit_card/frontend/build/precache-manifest.75bb9f3585c81fa1fdeb8616b6e03916.js
streamlit_card/frontend/build/service-worker.js
streamlit_card/frontend/build/static/js/2.f9e75198.chunk.js
streamlit_card/frontend/build/static/js/2.f9e75198.chunk.js.map
streamlit_card/frontend/build/static/js/main.80cd56d8.chunk.js
streamlit_card/frontend/build/static/js/main.80cd56d8.chunk.js.map
streamlit_card/frontend/build/static/js/runtime~main.d653cc00.js
streamlit_card/frontend/build/static/js/runtime~main.d653cc00.js.map
streamlit_card-1.0.2.dist-info/LICENSE
streamlit_card-1.0.2.dist-info/METADATA
streamlit_card-1.0.2.dist-info/WHEEL
streamlit_card-1.0.2.dist-info/top_level.txt
streamlit_card-1.0.2.dist-info/RECORD
