Metadata-Version: 2.1
Name: streamlit-card
Version: 1.0.2
Summary: A streamlit component, to make UI cards
Home-page: https://github.com/gamcoh/st-card
Author: gamcoh
Author-email: cohengamliel8@gmail.com
Keywords: card streamlit streamlit-component
Classifier: Programming Language :: Python :: 3
Classifier: Operating System :: OS Independent
Classifier: License :: OSI Approved :: MIT License
Requires-Python: >=3.8
License-File: LICENSE
Requires-Dist: streamlit>=0.63
